{
    "DPAD_CONFIG": "03808FB0",
    "DPAD_TEXTURE": "0380B0C0",
    "EXT_MSG_DATA_FILE": "03809798",
    "EXT_MSG_TABLE": "0380A0B8",
    "EXT_MSG_TABLE_COUNT": "03809760",
    "EXT_OBJECTS": "038097B8",
    "FONT_TEXTURE": "0380C0C0",
    "G_C_HEAP": "03820000",
    "G_PAYLOAD_ADDR": "03800000",
    "HASH_ICONS": "0380903C",
    "HUD_COLOR_CONFIG": "03809110",
    "ITEM_OVERRIDE_COUNT": "0380971C",
    "ITEM_OVERRIDE_ENTRIES": "03809838",
    "MISC_CONFIG": "0380955C",
    "MMR_CONFIG": "03809580",
    "PAYLOAD_END": "0380D590",
    "PAYLOAD_START": "03800000",
    "SAVE_FILE_CONFIG": "038096C0",
    "TOWN_FAIRY_BYTES": "0380A340",
    "WORLD_COLOR_CONFIG": "038096DC",
    "amount_definite": "03809728",
    "amount_singular": "03809730",
    "article_definite": "03809748",
    "article_empty": "03809740",
    "article_indefinite": "03809758",
    "article_indefinite_vowel": "03809750",
    "dpad_sprite": "038090D8",
    "fairy_sprite": "03809098",
    "font_sprite": "038090C8",
    "g_external_effects": "03808FCC",
    "g_objheap": "0380A2B8",
    "g_objheap_items": "0380A2E0",
    "heap_next": "038097B4",
    "icon_24_sprite": "038090A8",
    "icon_sprite": "038090B8",
    "pronoun_singular": "03809738",
    "roll_targets": "03808F64",
    "setup_db": "038090E8",
    "verb_singular": "03809720"
}
